{"group": "KXAIRDROPMONAD", "count": 5, "markets": [{"ticker": "KXAIRDROPMONAD-26JAN01", "event_ticker": "KXAIRDROPMONAD", "market_type": "binary", "title": "Will Monad conduct an airdrop before Jan 1, 2026?", "subtitle": "", "yes_sub_title": "Before Jan 1, 2026", "no_sub_title": "Before Jan 1, 2026", "open_time": "2025-08-27T14:00:00Z", "close_time": "2026-01-01T04:59:00Z", "expected_expiration_time": "2026-02-01T15:00:00Z", "expiration_time": "2026-01-08T15:00:00Z", "latest_expiration_time": "2026-01-08T15:00:00Z", "settlement_timer_seconds": 1800, "status": "active", "response_price_units": "usd_cent", "notional_value": 100, "notional_value_dollars": [0, 0], "yes_bid": 89, "yes_bid_dollars": [0, 0], "yes_ask": 97, "yes_ask_dollars": [0, 0], "no_bid": 3, "no_bid_dollars": [0, 0], "no_ask": 11, "no_ask_dollars": [0, 0], "last_price": 88, "last_price_dollars": [0, 0], "previous_yes_bid": 84, "previous_yes_bid_dollars": [0, 0], "previous_yes_ask": 88, "previous_yes_ask_dollars": [0, 0], "previous_price": 88, "previous_price_dollars": [0, 0], "volume": 8, "volume_24h": 0, "liquidity": 300500, "liquidity_dollars": [0, 0], "open_interest": 8, "result": "", "can_close_early": true, "expiration_value": "", "category": "", "risk_limit_cents": 0, "yes_topbook_liquidity_dollars": [0, 0], "no_topbook_liquidity_dollars": [0, 0], "strike_type": "custom", "custom_strike": {"Date Range": "Before Jan 1, 2026"}, "rules_primary": "If Monad conducts an airdrop before Jan 1, 2026, then the market resolves to Yes.", "rules_secondary": "An airdrop is defined as the distribution of fungible tokens to multiple wallet addresses where recipients receive tokens without paying the full market value. This includes free distributions requiring only gas fees, distributions requiring donations less than 10% of market value, retroactive rewards, task-based distributions, and phased distributions where initial tokens are received before the deadline. Token sales where recipients pay 10% or more of market value, ICOs, IDOs, employee compensation, liquidity mining rewards, staking rewards, NFTs, non-transferable tokens, and unconverted points do not constitute airdrops. The airdrop must be conducted (tokens actually distributed) before the deadline, not merely announced.", "early_close_condition": "This market will close and expire early if the airdrop is announced and conducted.", "tick_size": 1}, {"ticker": "KXAIRDROPMONAD-26FEB01", "event_ticker": "KXAIRDROPMONAD", "market_type": "binary", "title": "Will Monad conduct an airdrop before Feb 1, 2026?", "subtitle": "", "yes_sub_title": "Before Feb 1, 2026", "no_sub_title": "Before Feb 1, 2026", "open_time": "2025-08-27T14:00:00Z", "close_time": "2026-02-01T04:59:00Z", "expected_expiration_time": "2026-02-01T15:00:00Z", "expiration_time": "2026-02-08T15:00:00Z", "latest_expiration_time": "2026-02-08T15:00:00Z", "settlement_timer_seconds": 1800, "status": "active", "response_price_units": "usd_cent", "notional_value": 100, "notional_value_dollars": [0, 0], "yes_bid": 91, "yes_bid_dollars": [0, 0], "yes_ask": 99, "yes_ask_dollars": [0, 0], "no_bid": 1, "no_bid_dollars": [0, 0], "no_ask": 9, "no_ask_dollars": [0, 0], "last_price": 0, "last_price_dollars": [0, 0], "previous_yes_bid": 86, "previous_yes_bid_dollars": [0, 0], "previous_yes_ask": 92, "previous_yes_ask_dollars": [0, 0], "previous_price": 0, "previous_price_dollars": [0, 0], "volume": 0, "volume_24h": 0, "liquidity": 218400, "liquidity_dollars": [0, 0], "open_interest": 0, "result": "", "can_close_early": true, "expiration_value": "", "category": "", "risk_limit_cents": 0, "yes_topbook_liquidity_dollars": [0, 0], "no_topbook_liquidity_dollars": [0, 0], "strike_type": "custom", "custom_strike": {"Date Range": "Before Feb 1, 2026"}, "rules_primary": "If Monad conducts an airdrop before Feb 1, 2026, then the market resolves to Yes.", "rules_secondary": "An airdrop is defined as the distribution of fungible tokens to multiple wallet addresses where recipients receive tokens without paying the full market value. This includes free distributions requiring only gas fees, distributions requiring donations less than 10% of market value, retroactive rewards, task-based distributions, and phased distributions where initial tokens are received before the deadline. Token sales where recipients pay 10% or more of market value, ICOs, IDOs, employee compensation, liquidity mining rewards, staking rewards, NFTs, non-transferable tokens, and unconverted points do not constitute airdrops. The airdrop must be conducted (tokens actually distributed) before the deadline, not merely announced.", "early_close_condition": "This market will close and expire early if the airdrop is announced and conducted.", "tick_size": 1}, {"ticker": "KXAIRDROPMONAD-25OCT01", "event_ticker": "KXAIRDROPMONAD", "market_type": "binary", "title": "Will Monad conduct an airdrop before Oct 1, 2025?", "subtitle": "", "yes_sub_title": "Before Oct 1, 2025", "no_sub_title": "Before Oct 1, 2025", "open_time": "2025-08-27T14:00:00Z", "close_time": "2025-10-01T03:59:00Z", "expected_expiration_time": "2026-02-01T15:00:00Z", "expiration_time": "2025-10-08T14:00:00Z", "latest_expiration_time": "2025-10-08T14:00:00Z", "settlement_timer_seconds": 1800, "status": "active", "response_price_units": "usd_cent", "notional_value": 100, "notional_value_dollars": [0, 0], "yes_bid": 27, "yes_bid_dollars": [0, 0], "yes_ask": 33, "yes_ask_dollars": [0, 0], "no_bid": 67, "no_bid_dollars": [0, 0], "no_ask": 73, "no_ask_dollars": [0, 0], "last_price": 28, "last_price_dollars": [0, 0], "previous_yes_bid": 17, "previous_yes_bid_dollars": [0, 0], "previous_yes_ask": 23, "previous_yes_ask_dollars": [0, 0], "previous_price": 17, "previous_price_dollars": [0, 0], "volume": 2374, "volume_24h": 865, "liquidity": 3551016, "liquidity_dollars": [0, 0], "open_interest": 942, "result": "", "can_close_early": true, "expiration_value": "", "category": "", "risk_limit_cents": 0, "yes_topbook_liquidity_dollars": [0, 0], "no_topbook_liquidity_dollars": [0, 0], "strike_type": "custom", "custom_strike": {"Date Range": "Before Oct 1, 2025"}, "rules_primary": "If Monad conducts an airdrop before Oct 1, 2025, then the market resolves to Yes.", "rules_secondary": "An airdrop is defined as the distribution of fungible tokens to multiple wallet addresses where recipients receive tokens without paying the full market value. This includes free distributions requiring only gas fees, distributions requiring donations less than 10% of market value, retroactive rewards, task-based distributions, and phased distributions where initial tokens are received before the deadline. Token sales where recipients pay 10% or more of market value, ICOs, IDOs, employee compensation, liquidity mining rewards, staking rewards, NFTs, non-transferable tokens, and unconverted points do not constitute airdrops. The airdrop must be conducted (tokens actually distributed) before the deadline, not merely announced.", "early_close_condition": "This market will close and expire early if the airdrop is announced and conducted.", "tick_size": 1}, {"ticker": "KXAIRDROPMONAD-25NOV01", "event_ticker": "KXAIRDROPMONAD", "market_type": "binary", "title": "Will Monad conduct an airdrop before Nov 1, 2025?", "subtitle": "", "yes_sub_title": "Before Nov 1, 2025", "no_sub_title": "Before Nov 1, 2025", "open_time": "2025-08-27T14:00:00Z", "close_time": "2025-11-01T03:59:00Z", "expected_expiration_time": "2026-02-01T15:00:00Z", "expiration_time": "2025-11-08T14:00:00Z", "latest_expiration_time": "2025-11-08T14:00:00Z", "settlement_timer_seconds": 1800, "status": "active", "response_price_units": "usd_cent", "notional_value": 100, "notional_value_dollars": [0, 0], "yes_bid": 64, "yes_bid_dollars": [0, 0], "yes_ask": 72, "yes_ask_dollars": [0, 0], "no_bid": 28, "no_bid_dollars": [0, 0], "no_ask": 36, "no_ask_dollars": [0, 0], "last_price": 0, "last_price_dollars": [0, 0], "previous_yes_bid": 37, "previous_yes_bid_dollars": [0, 0], "previous_yes_ask": 43, "previous_yes_ask_dollars": [0, 0], "previous_price": 0, "previous_price_dollars": [0, 0], "volume": 0, "volume_24h": 0, "liquidity": 632614, "liquidity_dollars": [0, 0], "open_interest": 0, "result": "", "can_close_early": true, "expiration_value": "", "category": "", "risk_limit_cents": 0, "yes_topbook_liquidity_dollars": [0, 0], "no_topbook_liquidity_dollars": [0, 0], "strike_type": "custom", "custom_strike": {"Date Range": "Before Nov 1, 2025"}, "rules_primary": "If Monad conducts an airdrop before Nov 1, 2025, then the market resolves to Yes.", "rules_secondary": "An airdrop is defined as the distribution of fungible tokens to multiple wallet addresses where recipients receive tokens without paying the full market value. This includes free distributions requiring only gas fees, distributions requiring donations less than 10% of market value, retroactive rewards, task-based distributions, and phased distributions where initial tokens are received before the deadline. Token sales where recipients pay 10% or more of market value, ICOs, IDOs, employee compensation, liquidity mining rewards, staking rewards, NFTs, non-transferable tokens, and unconverted points do not constitute airdrops. The airdrop must be conducted (tokens actually distributed) before the deadline, not merely announced.", "early_close_condition": "This market will close and expire early if the airdrop is announced and conducted.", "tick_size": 1}, {"ticker": "KXAIRDROPMONAD-25DEC01", "event_ticker": "KXAIRDROPMONAD", "market_type": "binary", "title": "Will Monad conduct an airdrop before Dec 1, 2025?", "subtitle": "", "yes_sub_title": "Before Dec 1, 2025", "no_sub_title": "Before Dec 1, 2025", "open_time": "2025-08-27T14:00:00Z", "close_time": "2025-12-01T04:59:00Z", "expected_expiration_time": "2026-02-01T15:00:00Z", "expiration_time": "2025-12-08T15:00:00Z", "latest_expiration_time": "2025-12-08T15:00:00Z", "settlement_timer_seconds": 1800, "status": "active", "response_price_units": "usd_cent", "notional_value": 100, "notional_value_dollars": [0, 0], "yes_bid": 75, "yes_bid_dollars": [0, 0], "yes_ask": 82, "yes_ask_dollars": [0, 0], "no_bid": 18, "no_bid_dollars": [0, 0], "no_ask": 25, "no_ask_dollars": [0, 0], "last_price": 67, "last_price_dollars": [0, 0], "previous_yes_bid": 63, "previous_yes_bid_dollars": [0, 0], "previous_yes_ask": 68, "previous_yes_ask_dollars": [0, 0], "previous_price": 67, "previous_price_dollars": [0, 0], "volume": 341, "volume_24h": 32, "liquidity": 2988356, "liquidity_dollars": [0, 0], "open_interest": 341, "result": "", "can_close_early": true, "expiration_value": "", "category": "", "risk_limit_cents": 0, "yes_topbook_liquidity_dollars": [0, 0], "no_topbook_liquidity_dollars": [0, 0], "strike_type": "custom", "custom_strike": {"Date Range": "Before Dec 1, 2025"}, "rules_primary": "If Monad conducts an airdrop before Dec 1, 2025, then the market resolves to Yes.", "rules_secondary": "An airdrop is defined as the distribution of fungible tokens to multiple wallet addresses where recipients receive tokens without paying the full market value. This includes free distributions requiring only gas fees, distributions requiring donations less than 10% of market value, retroactive rewards, task-based distributions, and phased distributions where initial tokens are received before the deadline. Token sales where recipients pay 10% or more of market value, ICOs, IDOs, employee compensation, liquidity mining rewards, staking rewards, NFTs, non-transferable tokens, and unconverted points do not constitute airdrops. The airdrop must be conducted (tokens actually distributed) before the deadline, not merely announced.", "early_close_condition": "This market will close and expire early if the airdrop is announced and conducted.", "tick_size": 1}]}