{"group": "KXCOMMISHFDA", "count": 5, "markets": [{"ticker": "KXCOMMISHFDA-25-MAY", "event_ticker": "KXCOMMISHFDA-25", "market_type": "binary", "title": "When will Trump's nominee for Commissioner of the FDA be confirmed?", "subtitle": "", "yes_sub_title": "Before May 2025", "no_sub_title": "Before May 2025", "open_time": "2025-03-15T14:00:00Z", "close_time": "2025-03-27T14:18:03.5533Z", "expected_expiration_time": "2025-12-02T15:00:00Z", "expiration_time": "2025-05-01T14:00:00Z", "latest_expiration_time": "2025-05-01T14:00:00Z", "settlement_timer_seconds": 1800, "status": "finalized", "response_price_units": "usd_cent", "notional_value": 100, "notional_value_dollars": [0, 0], "yes_bid": 99, "yes_bid_dollars": [0, 0], "yes_ask": 100, "yes_ask_dollars": [0, 0], "no_bid": 0, "no_bid_dollars": [0, 0], "no_ask": 1, "no_ask_dollars": [0, 0], "last_price": 99, "last_price_dollars": [0, 0], "previous_yes_bid": 99, "previous_yes_bid_dollars": [0, 0], "previous_yes_ask": 100, "previous_yes_ask_dollars": [0, 0], "previous_price": 99, "previous_price_dollars": [0, 0], "volume": 125, "volume_24h": 0, "liquidity": 0, "liquidity_dollars": [0, 0], "open_interest": 125, "result": "yes", "settlement_value": 100, "can_close_early": true, "expiration_value": "Yes", "category": "", "risk_limit_cents": 0, "yes_topbook_liquidity_dollars": [0, 0], "no_topbook_liquidity_dollars": [0, 0], "strike_type": "custom", "custom_strike": {"Person": "Marty Makary"}, "rules_primary": "If Marty Makary is the first person confirmed by the Senate to be Commissioner of the FDA before May 1, 2025, then the market resolves to Yes.", "rules_secondary": "", "tick_size": 1}, {"ticker": "KXCOMMISHFDA-25-JUN", "event_ticker": "KXCOMMISHFDA-25", "market_type": "binary", "title": "When will Trump's nominee for Commissioner of the FDA be confirmed?", "subtitle": "", "yes_sub_title": "Before Jun 2025", "no_sub_title": "Before Jun 2025", "open_time": "2025-03-15T14:00:00Z", "close_time": "2025-03-27T14:18:18.351084Z", "expected_expiration_time": "2025-12-02T15:00:00Z", "expiration_time": "2025-06-01T14:00:00Z", "latest_expiration_time": "2025-06-01T14:00:00Z", "settlement_timer_seconds": 1800, "status": "finalized", "response_price_units": "usd_cent", "notional_value": 100, "notional_value_dollars": [0, 0], "yes_bid": 99, "yes_bid_dollars": [0, 0], "yes_ask": 100, "yes_ask_dollars": [0, 0], "no_bid": 0, "no_bid_dollars": [0, 0], "no_ask": 1, "no_ask_dollars": [0, 0], "last_price": 99, "last_price_dollars": [0, 0], "previous_yes_bid": 99, "previous_yes_bid_dollars": [0, 0], "previous_yes_ask": 100, "previous_yes_ask_dollars": [0, 0], "previous_price": 99, "previous_price_dollars": [0, 0], "volume": 100, "volume_24h": 0, "liquidity": 0, "liquidity_dollars": [0, 0], "open_interest": 100, "result": "yes", "settlement_value": 100, "can_close_early": true, "expiration_value": "Yes", "category": "", "risk_limit_cents": 0, "yes_topbook_liquidity_dollars": [0, 0], "no_topbook_liquidity_dollars": [0, 0], "strike_type": "custom", "custom_strike": {"Person": "Marty Makary"}, "rules_primary": "If Marty Makary is the first person confirmed by the Senate to be Commissioner of the FDA before Jun 1, 2025, then the market resolves to Yes.", "rules_secondary": "", "tick_size": 1}, {"ticker": "KXCOMMISHFDA-25-JUL", "event_ticker": "KXCOMMISHFDA-25", "market_type": "binary", "title": "When will Trump's nominee for Commissioner of the FDA be confirmed?", "subtitle": "", "yes_sub_title": "Before Jul 2025", "no_sub_title": "Before Jul 2025", "open_time": "2025-03-15T14:00:00Z", "close_time": "2025-03-27T14:18:55.230876Z", "expected_expiration_time": "2025-12-02T15:00:00Z", "expiration_time": "2025-07-01T14:00:00Z", "latest_expiration_time": "2025-07-01T14:00:00Z", "settlement_timer_seconds": 1800, "status": "finalized", "response_price_units": "usd_cent", "notional_value": 100, "notional_value_dollars": [0, 0], "yes_bid": 99, "yes_bid_dollars": [0, 0], "yes_ask": 100, "yes_ask_dollars": [0, 0], "no_bid": 0, "no_bid_dollars": [0, 0], "no_ask": 1, "no_ask_dollars": [0, 0], "last_price": 99, "last_price_dollars": [0, 0], "previous_yes_bid": 99, "previous_yes_bid_dollars": [0, 0], "previous_yes_ask": 100, "previous_yes_ask_dollars": [0, 0], "previous_price": 99, "previous_price_dollars": [0, 0], "volume": 100, "volume_24h": 0, "liquidity": 0, "liquidity_dollars": [0, 0], "open_interest": 100, "result": "yes", "settlement_value": 100, "can_close_early": true, "expiration_value": "Yes", "category": "", "risk_limit_cents": 0, "yes_topbook_liquidity_dollars": [0, 0], "no_topbook_liquidity_dollars": [0, 0], "strike_type": "custom", "custom_strike": {"Person": "Marty Makary"}, "rules_primary": "If Marty Makary is the first person confirmed by the Senate to be Commissioner of the FDA before Jul 1, 2025, then the market resolves to Yes.", "rules_secondary": "", "tick_size": 1}, {"ticker": "KXCOMMISHFDA-25-DEC", "event_ticker": "KXCOMMISHFDA-25", "market_type": "binary", "title": "When will Trump's nominee for Commissioner of the FDA be confirmed?", "subtitle": "", "yes_sub_title": "Before Dec 2025", "no_sub_title": "Before Dec 2025", "open_time": "2025-03-15T14:00:00Z", "close_time": "2025-03-27T14:19:10.577384Z", "expected_expiration_time": "2025-12-02T15:00:00Z", "expiration_time": "2025-12-01T15:00:00Z", "latest_expiration_time": "2025-12-01T15:00:00Z", "settlement_timer_seconds": 1800, "status": "finalized", "response_price_units": "usd_cent", "notional_value": 100, "notional_value_dollars": [0, 0], "yes_bid": 99, "yes_bid_dollars": [0, 0], "yes_ask": 100, "yes_ask_dollars": [0, 0], "no_bid": 0, "no_bid_dollars": [0, 0], "no_ask": 1, "no_ask_dollars": [0, 0], "last_price": 95, "last_price_dollars": [0, 0], "previous_yes_bid": 99, "previous_yes_bid_dollars": [0, 0], "previous_yes_ask": 100, "previous_yes_ask_dollars": [0, 0], "previous_price": 95, "previous_price_dollars": [0, 0], "volume": 101, "volume_24h": 0, "liquidity": 0, "liquidity_dollars": [0, 0], "open_interest": 101, "result": "yes", "settlement_value": 100, "can_close_early": true, "expiration_value": "Yes", "category": "", "risk_limit_cents": 0, "yes_topbook_liquidity_dollars": [0, 0], "no_topbook_liquidity_dollars": [0, 0], "strike_type": "custom", "custom_strike": {"Person": "Marty Makary"}, "rules_primary": "If Marty Makary is the first person confirmed by the Senate to be Commissioner of the FDA before Dec 1, 2025, then the market resolves to Yes.", "rules_secondary": "", "tick_size": 1}, {"ticker": "KXCOMMISHFDA-25-APR", "event_ticker": "KXCOMMISHFDA-25", "market_type": "binary", "title": "When will Trump's nominee for Commissioner of the FDA be confirmed?", "subtitle": "", "yes_sub_title": "Before Apr 2025", "no_sub_title": "Before Apr 2025", "open_time": "2025-03-15T14:00:00Z", "close_time": "2025-03-27T14:17:47.471336Z", "expected_expiration_time": "2025-12-02T15:00:00Z", "expiration_time": "2025-04-01T14:00:00Z", "latest_expiration_time": "2025-04-01T14:00:00Z", "settlement_timer_seconds": 1800, "status": "finalized", "response_price_units": "usd_cent", "notional_value": 100, "notional_value_dollars": [0, 0], "yes_bid": 99, "yes_bid_dollars": [0, 0], "yes_ask": 100, "yes_ask_dollars": [0, 0], "no_bid": 0, "no_bid_dollars": [0, 0], "no_ask": 1, "no_ask_dollars": [0, 0], "last_price": 93, "last_price_dollars": [0, 0], "previous_yes_bid": 99, "previous_yes_bid_dollars": [0, 0], "previous_yes_ask": 100, "previous_yes_ask_dollars": [0, 0], "previous_price": 93, "previous_price_dollars": [0, 0], "volume": 1464, "volume_24h": 0, "liquidity": 0, "liquidity_dollars": [0, 0], "open_interest": 1214, "result": "yes", "settlement_value": 100, "can_close_early": true, "expiration_value": "Yes", "category": "", "risk_limit_cents": 0, "yes_topbook_liquidity_dollars": [0, 0], "no_topbook_liquidity_dollars": [0, 0], "strike_type": "custom", "custom_strike": {"Person": "Marty Makary"}, "rules_primary": "If Marty Makary is the first person confirmed by the Senate to be Commissioner of the FDA before Apr 1, 2025, then the market resolves to Yes.", "rules_secondary": "", "tick_size": 1}]}