{"group": "TNOTE", "count": 18, "markets": [{"ticker": "TNOTE-22MAR07-T2.0", "event_ticker": "TNOTE-22MAR07", "market_type": "binary", "title": "Will the yield of 10-year **U.S. treasury notes** be above 2.0% on March 07, 2022?", "subtitle": ">2.0%", "yes_sub_title": "2.00%", "no_sub_title": "Outside 2.00%", "open_time": "2022-03-01T15:00:00Z", "close_time": "2022-03-07T20:25:00Z", "expected_expiration_time": "2022-03-01T15:00:00Z", "expiration_time": "2022-03-14T15:00:00Z", "latest_expiration_time": "2022-03-14T15:00:00Z", "settlement_timer_seconds": 10800, "status": "finalized", "response_price_units": "usd_cent", "notional_value": 100, "notional_value_dollars": [0, 0], "yes_bid": 0, "yes_bid_dollars": [0, 0], "yes_ask": 1, "yes_ask_dollars": [0, 0], "no_bid": 99, "no_bid_dollars": [0, 0], "no_ask": 100, "no_ask_dollars": [0, 0], "last_price": 2, "last_price_dollars": [0, 0], "previous_yes_bid": 0, "previous_yes_bid_dollars": [0, 0], "previous_yes_ask": 1, "previous_yes_ask_dollars": [0, 0], "previous_price": 2, "previous_price_dollars": [0, 0], "volume": 2189, "volume_24h": 0, "liquidity": 0, "liquidity_dollars": [0, 0], "open_interest": 2179, "result": "no", "settlement_value": 0, "can_close_early": true, "expiration_value": "1.78", "category": "", "risk_limit_cents": 0, "yes_topbook_liquidity_dollars": [0, 0], "no_topbook_liquidity_dollars": [0, 0], "rules_primary": "If the yield curve par rate for 10-year U.S. treasury notes is above 2.0% on March 07, 2022, then the market resolves to Yes.", "rules_secondary": "The market will close at the 3:25 PM ET on March 07, 2022.", "tick_size": 1}, {"ticker": "TNOTE-22MAR07-T1.9", "event_ticker": "TNOTE-22MAR07", "market_type": "binary", "title": "Will the yield of 10-year **U.S. treasury notes** be above 1.9% on March 07, 2022?", "subtitle": ">1.9%", "yes_sub_title": "1.90%", "no_sub_title": "Outside 1.90%", "open_time": "2022-03-01T15:00:00Z", "close_time": "2022-03-07T20:25:00Z", "expected_expiration_time": "2022-03-01T15:00:00Z", "expiration_time": "2022-03-14T15:00:00Z", "latest_expiration_time": "2022-03-14T15:00:00Z", "settlement_timer_seconds": 10800, "status": "finalized", "response_price_units": "usd_cent", "notional_value": 100, "notional_value_dollars": [0, 0], "yes_bid": 0, "yes_bid_dollars": [0, 0], "yes_ask": 1, "yes_ask_dollars": [0, 0], "no_bid": 99, "no_bid_dollars": [0, 0], "no_ask": 100, "no_ask_dollars": [0, 0], "last_price": 2, "last_price_dollars": [0, 0], "previous_yes_bid": 0, "previous_yes_bid_dollars": [0, 0], "previous_yes_ask": 1, "previous_yes_ask_dollars": [0, 0], "previous_price": 2, "previous_price_dollars": [0, 0], "volume": 1876, "volume_24h": 0, "liquidity": 0, "liquidity_dollars": [0, 0], "open_interest": 1629, "result": "no", "settlement_value": 0, "can_close_early": true, "expiration_value": "1.78", "category": "", "risk_limit_cents": 0, "yes_topbook_liquidity_dollars": [0, 0], "no_topbook_liquidity_dollars": [0, 0], "rules_primary": "If the yield curve par rate for 10-year U.S. treasury notes is above 1.9% on March 07, 2022, then the market resolves to Yes.", "rules_secondary": "The market will close at the 3:25 PM ET on March 07, 2022.", "tick_size": 1}, {"ticker": "TNOTE-22MAR07-T1.8", "event_ticker": "TNOTE-22MAR07", "market_type": "binary", "title": "Will the yield of 10-year U.S. treasury notes be above 1.8% on March 07, 2022?", "subtitle": ">1.8%", "yes_sub_title": "1.80%", "no_sub_title": "Outside 1.80%", "open_time": "2022-03-01T15:00:00Z", "close_time": "2022-03-07T20:25:00Z", "expected_expiration_time": "2022-03-01T15:00:00Z", "expiration_time": "2022-03-14T15:00:00Z", "latest_expiration_time": "2022-03-14T15:00:00Z", "settlement_timer_seconds": 10800, "status": "finalized", "response_price_units": "usd_cent", "notional_value": 100, "notional_value_dollars": [0, 0], "yes_bid": 0, "yes_bid_dollars": [0, 0], "yes_ask": 1, "yes_ask_dollars": [0, 0], "no_bid": 99, "no_bid_dollars": [0, 0], "no_ask": 100, "no_ask_dollars": [0, 0], "last_price": 1, "last_price_dollars": [0, 0], "previous_yes_bid": 0, "previous_yes_bid_dollars": [0, 0], "previous_yes_ask": 1, "previous_yes_ask_dollars": [0, 0], "previous_price": 1, "previous_price_dollars": [0, 0], "volume": 4270, "volume_24h": 1834, "liquidity": 0, "liquidity_dollars": [0, 0], "open_interest": 1500, "result": "no", "settlement_value": 0, "can_close_early": true, "expiration_value": "1.78", "category": "", "risk_limit_cents": 0, "yes_topbook_liquidity_dollars": [0, 0], "no_topbook_liquidity_dollars": [0, 0], "rules_primary": "If the yield curve par rate for 10-year U.S. treasury notes is above 1.8% on March 07, 2022, then the market resolves to Yes.", "rules_secondary": "The market will close at the 3:25 PM ET on March 07, 2022.", "tick_size": 1}, {"ticker": "TNOTE-22FEB28-T2.0", "event_ticker": "TNOTE-22FEB28", "market_type": "binary", "title": "Will the yield of 10-year U.S. treasury notes be above 2.0% on February 28, 2022?", "subtitle": ">2.0%", "yes_sub_title": "2.00%", "no_sub_title": "Outside 2.00%", "open_time": "2022-02-23T15:00:00Z", "close_time": "2022-02-28T20:25:00Z", "expected_expiration_time": "2022-02-23T15:00:00Z", "expiration_time": "2022-03-07T15:00:00Z", "latest_expiration_time": "2022-03-07T15:00:00Z", "settlement_timer_seconds": 10800, "status": "finalized", "response_price_units": "usd_cent", "notional_value": 100, "notional_value_dollars": [0, 0], "yes_bid": 0, "yes_bid_dollars": [0, 0], "yes_ask": 1, "yes_ask_dollars": [0, 0], "no_bid": 99, "no_bid_dollars": [0, 0], "no_ask": 100, "no_ask_dollars": [0, 0], "last_price": 1, "last_price_dollars": [0, 0], "previous_yes_bid": 0, "previous_yes_bid_dollars": [0, 0], "previous_yes_ask": 1, "previous_yes_ask_dollars": [0, 0], "previous_price": 1, "previous_price_dollars": [0, 0], "volume": 1772, "volume_24h": 0, "liquidity": 0, "liquidity_dollars": [0, 0], "open_interest": 237, "result": "no", "settlement_value": 0, "can_close_early": true, "expiration_value": "1.83", "category": "", "risk_limit_cents": 0, "yes_topbook_liquidity_dollars": [0, 0], "no_topbook_liquidity_dollars": [0, 0], "rules_primary": "If the yield curve par rate for 10-year U.S. treasury notes is above 2.0% on February 28, 2022, then the market resolves to Yes.", "rules_secondary": "The market will close at the 3:25 PM ET on February 28, 2022.", "tick_size": 1}, {"ticker": "TNOTE-22FEB28-T1.95", "event_ticker": "TNOTE-22FEB28", "market_type": "binary", "title": "Will the yield of 10-year U.S. treasury notes be above 1.95% on February 28, 2022?", "subtitle": ">1.95%", "yes_sub_title": "1.95%", "no_sub_title": "Outside 1.95%", "open_time": "2022-02-23T15:00:00Z", "close_time": "2022-02-28T20:25:00Z", "expected_expiration_time": "2022-02-23T15:00:00Z", "expiration_time": "2022-03-07T15:00:00Z", "latest_expiration_time": "2022-03-07T15:00:00Z", "settlement_timer_seconds": 10800, "status": "finalized", "response_price_units": "usd_cent", "notional_value": 100, "notional_value_dollars": [0, 0], "yes_bid": 0, "yes_bid_dollars": [0, 0], "yes_ask": 2, "yes_ask_dollars": [0, 0], "no_bid": 98, "no_bid_dollars": [0, 0], "no_ask": 100, "no_ask_dollars": [0, 0], "last_price": 2, "last_price_dollars": [0, 0], "previous_yes_bid": 0, "previous_yes_bid_dollars": [0, 0], "previous_yes_ask": 2, "previous_yes_ask_dollars": [0, 0], "previous_price": 2, "previous_price_dollars": [0, 0], "volume": 7703, "volume_24h": 1565, "liquidity": 0, "liquidity_dollars": [0, 0], "open_interest": 2698, "result": "no", "settlement_value": 0, "can_close_early": true, "expiration_value": "1.83", "category": "", "risk_limit_cents": 0, "yes_topbook_liquidity_dollars": [0, 0], "no_topbook_liquidity_dollars": [0, 0], "rules_primary": "If the yield curve par rate for 10-year U.S. treasury notes is above 1.95% on February 28, 2022, then the market resolves to Yes.", "rules_secondary": "The market will close at the 3:25 PM ET on February 28, 2022.", "tick_size": 1}, {"ticker": "TNOTE-22FEB28-T1.9", "event_ticker": "TNOTE-22FEB28", "market_type": "binary", "title": "Will the yield of 10-year U.S. treasury notes be above 1.9% on February 28, 2022?", "subtitle": ">1.9%", "yes_sub_title": "1.90%", "no_sub_title": "Outside 1.90%", "open_time": "2022-02-23T15:00:00Z", "close_time": "2022-02-28T20:25:00Z", "expected_expiration_time": "2022-02-23T15:00:00Z", "expiration_time": "2022-03-07T15:00:00Z", "latest_expiration_time": "2022-03-07T15:00:00Z", "settlement_timer_seconds": 10800, "status": "finalized", "response_price_units": "usd_cent", "notional_value": 100, "notional_value_dollars": [0, 0], "yes_bid": 0, "yes_bid_dollars": [0, 0], "yes_ask": 2, "yes_ask_dollars": [0, 0], "no_bid": 98, "no_bid_dollars": [0, 0], "no_ask": 100, "no_ask_dollars": [0, 0], "last_price": 15, "last_price_dollars": [0, 0], "previous_yes_bid": 0, "previous_yes_bid_dollars": [0, 0], "previous_yes_ask": 2, "previous_yes_ask_dollars": [0, 0], "previous_price": 15, "previous_price_dollars": [0, 0], "volume": 6204, "volume_24h": 506, "liquidity": 0, "liquidity_dollars": [0, 0], "open_interest": 1311, "result": "no", "settlement_value": 0, "can_close_early": true, "expiration_value": "1.83", "category": "", "risk_limit_cents": 0, "yes_topbook_liquidity_dollars": [0, 0], "no_topbook_liquidity_dollars": [0, 0], "rules_primary": "If the yield curve par rate for 10-year U.S. treasury notes is above 1.9% on February 28, 2022, then the market resolves to Yes.", "rules_secondary": "The market will close at the 3:25 PM ET on February 28, 2022.", "tick_size": 1}, {"ticker": "TNOTE-22FEB22-T2.1", "event_ticker": "TNOTE-22FEB22", "market_type": "binary", "title": "Will the yield of 10-year U.S. treasury notes be above 2.1% on February 22, 2022?", "subtitle": ">2.1%", "yes_sub_title": "2.10%", "no_sub_title": "Outside 2.10%", "open_time": "2022-02-15T15:00:00Z", "close_time": "2022-02-22T20:25:00Z", "expected_expiration_time": "2022-02-15T15:00:00Z", "expiration_time": "2022-03-01T15:00:00Z", "latest_expiration_time": "2022-03-01T15:00:00Z", "settlement_timer_seconds": 10800, "status": "finalized", "response_price_units": "usd_cent", "notional_value": 100, "notional_value_dollars": [0, 0], "yes_bid": 0, "yes_bid_dollars": [0, 0], "yes_ask": 2, "yes_ask_dollars": [0, 0], "no_bid": 98, "no_bid_dollars": [0, 0], "no_ask": 100, "no_ask_dollars": [0, 0], "last_price": 3, "last_price_dollars": [0, 0], "previous_yes_bid": 0, "previous_yes_bid_dollars": [0, 0], "previous_yes_ask": 2, "previous_yes_ask_dollars": [0, 0], "previous_price": 3, "previous_price_dollars": [0, 0], "volume": 1555, "volume_24h": 0, "liquidity": 0, "liquidity_dollars": [0, 0], "open_interest": 436, "result": "no", "settlement_value": 0, "can_close_early": true, "expiration_value": "1.94", "category": "", "risk_limit_cents": 0, "yes_topbook_liquidity_dollars": [0, 0], "no_topbook_liquidity_dollars": [0, 0], "rules_primary": "If the yield curve par rate for 10-year U.S. treasury notes is above 2.1% on February 22, 2022, then the market resolves to Yes.", "rules_secondary": "The market will expire and close and expire at the sooner of the first 10:00 AM following the data release for February 22, 2022, or one week following February 22, 2022.\n\nPlease note that while this Contract's target date normally corresponds to a Monday, due to the federal holiday, the target date (February 22) corresponds to a Tuesday.", "tick_size": 1}, {"ticker": "TNOTE-22FEB22-T2.0", "event_ticker": "TNOTE-22FEB22", "market_type": "binary", "title": "Will the yield of 10-year U.S. treasury notes be above 2.0% on February 22, 2022?", "subtitle": ">2.0%", "yes_sub_title": "2.00%", "no_sub_title": "Outside 2.00%", "open_time": "2022-02-15T15:00:00Z", "close_time": "2022-02-22T20:25:00Z", "expected_expiration_time": "2022-02-15T15:00:00Z", "expiration_time": "2022-03-01T15:00:00Z", "latest_expiration_time": "2022-03-01T15:00:00Z", "settlement_timer_seconds": 10800, "status": "finalized", "response_price_units": "usd_cent", "notional_value": 100, "notional_value_dollars": [0, 0], "yes_bid": 0, "yes_bid_dollars": [0, 0], "yes_ask": 1, "yes_ask_dollars": [0, 0], "no_bid": 99, "no_bid_dollars": [0, 0], "no_ask": 100, "no_ask_dollars": [0, 0], "last_price": 1, "last_price_dollars": [0, 0], "previous_yes_bid": 0, "previous_yes_bid_dollars": [0, 0], "previous_yes_ask": 1, "previous_yes_ask_dollars": [0, 0], "previous_price": 1, "previous_price_dollars": [0, 0], "volume": 2186, "volume_24h": 263, "liquidity": 0, "liquidity_dollars": [0, 0], "open_interest": 1115, "result": "no", "settlement_value": 0, "can_close_early": true, "expiration_value": "1.94", "category": "", "risk_limit_cents": 0, "yes_topbook_liquidity_dollars": [0, 0], "no_topbook_liquidity_dollars": [0, 0], "rules_primary": "If the yield curve par rate for 10-year U.S. treasury notes is above 2.1% on February 22, 2022, then the market resolves to Yes.", "rules_secondary": "The market will expire and close and expire at the sooner of the first 10:00 AM following the data release for February 22, 2022, or one week following February 22, 2022.\n\nPlease note that while this Contract's target date normally corresponds to a Monday, due to the federal holiday, the target date (February 22) corresponds to a Tuesday.", "tick_size": 1}, {"ticker": "TNOTE-22FEB22-T1.9", "event_ticker": "TNOTE-22FEB22", "market_type": "binary", "title": "Will the yield of 10-year U.S. treasury notes be above 1.9% on February 22, 2022?", "subtitle": ">1.9%", "yes_sub_title": "1.90%", "no_sub_title": "Outside 1.90%", "open_time": "2022-02-15T15:00:00Z", "close_time": "2022-02-22T20:25:00Z", "expected_expiration_time": "2022-02-15T15:00:00Z", "expiration_time": "2022-03-01T15:00:00Z", "latest_expiration_time": "2022-03-01T15:00:00Z", "settlement_timer_seconds": 10800, "status": "finalized", "response_price_units": "usd_cent", "notional_value": 100, "notional_value_dollars": [0, 0], "yes_bid": 99, "yes_bid_dollars": [0, 0], "yes_ask": 100, "yes_ask_dollars": [0, 0], "no_bid": 0, "no_bid_dollars": [0, 0], "no_ask": 1, "no_ask_dollars": [0, 0], "last_price": 98, "last_price_dollars": [0, 0], "previous_yes_bid": 99, "previous_yes_bid_dollars": [0, 0], "previous_yes_ask": 100, "previous_yes_ask_dollars": [0, 0], "previous_price": 98, "previous_price_dollars": [0, 0], "volume": 8650, "volume_24h": 1768, "liquidity": 0, "liquidity_dollars": [0, 0], "open_interest": 2962, "result": "yes", "settlement_value": 100, "can_close_early": true, "expiration_value": "1.94", "category": "", "risk_limit_cents": 0, "yes_topbook_liquidity_dollars": [0, 0], "no_topbook_liquidity_dollars": [0, 0], "rules_primary": "If the yield curve par rate for 10-year U.S. treasury notes is above 2.1% on February 22, 2022, then the market resolves to Yes.", "rules_secondary": "The market will expire and close and expire at the sooner of the first 10:00 AM following the data release for February 22, 2022, or one week following February 22, 2022.\n\nPlease note that while this Contract's target date normally corresponds to a Monday, due to the federal holiday, the target date (February 22) corresponds to a Tuesday.", "tick_size": 1}, {"ticker": "TNOTE-22FEB14-T1.8", "event_ticker": "TNOTE-22FEB14", "market_type": "binary", "title": "Will the yield of 10-year U.S. treasury notes be above 1.8% on February 14, 2022?", "subtitle": ">1.8%", "yes_sub_title": "1.80%", "no_sub_title": "Outside 1.80%", "open_time": "2022-02-08T15:00:00Z", "close_time": "2022-02-14T20:25:00Z", "expected_expiration_time": "2022-02-08T15:00:00Z", "expiration_time": "2022-02-21T15:00:00Z", "latest_expiration_time": "2022-02-21T15:00:00Z", "settlement_timer_seconds": 10800, "status": "finalized", "response_price_units": "usd_cent", "notional_value": 100, "notional_value_dollars": [0, 0], "yes_bid": 99, "yes_bid_dollars": [0, 0], "yes_ask": 100, "yes_ask_dollars": [0, 0], "no_bid": 0, "no_bid_dollars": [0, 0], "no_ask": 1, "no_ask_dollars": [0, 0], "last_price": 99, "last_price_dollars": [0, 0], "previous_yes_bid": 99, "previous_yes_bid_dollars": [0, 0], "previous_yes_ask": 100, "previous_yes_ask_dollars": [0, 0], "previous_price": 99, "previous_price_dollars": [0, 0], "volume": 1340, "volume_24h": 0, "liquidity": 0, "liquidity_dollars": [0, 0], "open_interest": 1090, "result": "yes", "settlement_value": 100, "can_close_early": true, "expiration_value": "1.98", "category": "", "risk_limit_cents": 0, "yes_topbook_liquidity_dollars": [0, 0], "no_topbook_liquidity_dollars": [0, 0], "rules_primary": "If the yield curve par rate for 10-year U.S. treasury notes is above 1.8% on February 14, 2022, then the market resolves to Yes.", "rules_secondary": "The market will expire and close and expire at the sooner of the first 10:00 AM following the data release for February 14, 2022, or one week following February 14, 2022.", "tick_size": 1}, {"ticker": "TNOTE-22FEB14-T2.0", "event_ticker": "TNOTE-22FEB14", "market_type": "binary", "title": "Will the yield of 10-year U.S. treasury notes be above 2.0% on February 14, 2022?", "subtitle": ">2.0%", "yes_sub_title": "2.00%", "no_sub_title": "Outside 2.00%", "open_time": "2022-02-08T15:00:00Z", "close_time": "2022-02-14T20:25:00Z", "expected_expiration_time": "2022-02-08T15:00:00Z", "expiration_time": "2022-02-21T15:00:00Z", "latest_expiration_time": "2022-02-21T15:00:00Z", "settlement_timer_seconds": 10800, "status": "finalized", "response_price_units": "usd_cent", "notional_value": 100, "notional_value_dollars": [0, 0], "yes_bid": 1, "yes_bid_dollars": [0, 0], "yes_ask": 10, "yes_ask_dollars": [0, 0], "no_bid": 90, "no_bid_dollars": [0, 0], "no_ask": 99, "no_ask_dollars": [0, 0], "last_price": 28, "last_price_dollars": [0, 0], "previous_yes_bid": 1, "previous_yes_bid_dollars": [0, 0], "previous_yes_ask": 10, "previous_yes_ask_dollars": [0, 0], "previous_price": 28, "previous_price_dollars": [0, 0], "volume": 7597, "volume_24h": 1059, "liquidity": 0, "liquidity_dollars": [0, 0], "open_interest": 2203, "result": "no", "settlement_value": 0, "can_close_early": true, "expiration_value": "1.98", "category": "", "risk_limit_cents": 0, "yes_topbook_liquidity_dollars": [0, 0], "no_topbook_liquidity_dollars": [0, 0], "rules_primary": "If the yield curve par rate for 10-year U.S. treasury notes is above 2.0% on February 14, 2022, then the market resolves to Yes.", "rules_secondary": "The market will expire and close and expire at the sooner of the first 10:00 AM following the data release for February 14, 2022, or one week following February 14, 2022.", "tick_size": 1}, {"ticker": "TNOTE-22FEB14-T1.9", "event_ticker": "TNOTE-22FEB14", "market_type": "binary", "title": "Will the yield of 10-year U.S. treasury notes be above 1.9% on February 14, 2022?", "subtitle": ">1.9%", "yes_sub_title": "1.90%", "no_sub_title": "Outside 1.90%", "open_time": "2022-02-08T15:00:00Z", "close_time": "2022-02-14T20:25:00Z", "expected_expiration_time": "2022-02-08T15:00:00Z", "expiration_time": "2022-02-21T15:00:00Z", "latest_expiration_time": "2022-02-21T15:00:00Z", "settlement_timer_seconds": 10800, "status": "finalized", "response_price_units": "usd_cent", "notional_value": 100, "notional_value_dollars": [0, 0], "yes_bid": 99, "yes_bid_dollars": [0, 0], "yes_ask": 100, "yes_ask_dollars": [0, 0], "no_bid": 0, "no_bid_dollars": [0, 0], "no_ask": 1, "no_ask_dollars": [0, 0], "last_price": 98, "last_price_dollars": [0, 0], "previous_yes_bid": 99, "previous_yes_bid_dollars": [0, 0], "previous_yes_ask": 100, "previous_yes_ask_dollars": [0, 0], "previous_price": 98, "previous_price_dollars": [0, 0], "volume": 6178, "volume_24h": 318, "liquidity": 0, "liquidity_dollars": [0, 0], "open_interest": 1401, "result": "yes", "settlement_value": 100, "can_close_early": true, "expiration_value": "1.98", "category": "", "risk_limit_cents": 0, "yes_topbook_liquidity_dollars": [0, 0], "no_topbook_liquidity_dollars": [0, 0], "rules_primary": "If the yield curve par rate for 10-year U.S. treasury notes is above 1.9% on February 14, 2022, then the market resolves to Yes.", "rules_secondary": "The market will expire and close and expire at the sooner of the first 10:00 AM following the data release for February 14, 2022, or one week following February 14, 2022.", "tick_size": 1}, {"ticker": "TNOTE-22FEB07-T1.9", "event_ticker": "TNOTE-22FEB07", "market_type": "binary", "title": "Will the yield of 10-year U.S. treasury notes be above 1.9% on February 07, 2022?", "subtitle": ">1.9%", "yes_sub_title": "1.90%", "no_sub_title": "Outside 1.90%", "open_time": "2022-02-01T15:00:00Z", "close_time": "2022-02-07T20:25:00Z", "expected_expiration_time": "2022-02-01T15:00:00Z", "expiration_time": "2022-02-14T15:00:00Z", "latest_expiration_time": "2022-02-14T15:00:00Z", "settlement_timer_seconds": 10800, "status": "finalized", "response_price_units": "usd_cent", "notional_value": 100, "notional_value_dollars": [0, 0], "yes_bid": 98, "yes_bid_dollars": [0, 0], "yes_ask": 100, "yes_ask_dollars": [0, 0], "no_bid": 0, "no_bid_dollars": [0, 0], "no_ask": 2, "no_ask_dollars": [0, 0], "last_price": 99, "last_price_dollars": [0, 0], "previous_yes_bid": 98, "previous_yes_bid_dollars": [0, 0], "previous_yes_ask": 100, "previous_yes_ask_dollars": [0, 0], "previous_price": 99, "previous_price_dollars": [0, 0], "volume": 5553, "volume_24h": 1153, "liquidity": 0, "liquidity_dollars": [0, 0], "open_interest": 1887, "result": "yes", "settlement_value": 100, "can_close_early": true, "expiration_value": "1.92", "category": "", "risk_limit_cents": 0, "yes_topbook_liquidity_dollars": [0, 0], "no_topbook_liquidity_dollars": [0, 0], "rules_primary": "If the yield curve par rate for 10-year U.S. treasury notes is above 1.9% on February 07, 2022, then the market resolves to Yes.", "rules_secondary": "These par yields are derived from bid-side market price quotations at or near 3:30 PM each trading day.\n\nThe market will expire and close and expire at the sooner of the first 10:00 AM following the data release for February 07, 2022, or one week following February 07, 2022.", "tick_size": 1}, {"ticker": "TNOTE-22FEB07-T1.8", "event_ticker": "TNOTE-22FEB07", "market_type": "binary", "title": "Will the yield of 10-year U.S. treasury notes be above 1.8% on February 07, 2022?", "subtitle": ">1.8%", "yes_sub_title": "1.80%", "no_sub_title": "Outside 1.80%", "open_time": "2022-02-01T15:00:00Z", "close_time": "2022-02-07T20:25:00Z", "expected_expiration_time": "2022-02-01T15:00:00Z", "expiration_time": "2022-02-14T15:00:00Z", "latest_expiration_time": "2022-02-14T15:00:00Z", "settlement_timer_seconds": 10800, "status": "finalized", "response_price_units": "usd_cent", "notional_value": 100, "notional_value_dollars": [0, 0], "yes_bid": 99, "yes_bid_dollars": [0, 0], "yes_ask": 100, "yes_ask_dollars": [0, 0], "no_bid": 0, "no_bid_dollars": [0, 0], "no_ask": 1, "no_ask_dollars": [0, 0], "last_price": 99, "last_price_dollars": [0, 0], "previous_yes_bid": 99, "previous_yes_bid_dollars": [0, 0], "previous_yes_ask": 100, "previous_yes_ask_dollars": [0, 0], "previous_price": 99, "previous_price_dollars": [0, 0], "volume": 3026, "volume_24h": 0, "liquidity": 0, "liquidity_dollars": [0, 0], "open_interest": 2151, "result": "yes", "settlement_value": 100, "can_close_early": true, "expiration_value": "1.92", "category": "", "risk_limit_cents": 0, "yes_topbook_liquidity_dollars": [0, 0], "no_topbook_liquidity_dollars": [0, 0], "rules_primary": "If the yield curve par rate for 10-year U.S. treasury notes is above 1.8% on February 07, 2022, then the market resolves to Yes.", "rules_secondary": "These par yields are derived from bid-side market price quotations at or near 3:30 PM each trading day.\n\nThe market will expire and close and expire at the sooner of the first 10:00 AM following the data release for February 07, 2022, or one week following February 07, 2022.", "tick_size": 1}, {"ticker": "TNOTE-22FEB07-T1.7", "event_ticker": "TNOTE-22FEB07", "market_type": "binary", "title": "Will the yield of 10-year U.S. treasury notes be above 1.7% on February 07, 2022?", "subtitle": ">1.7%", "yes_sub_title": "1.70%", "no_sub_title": "Outside 1.70%", "open_time": "2022-02-01T15:00:00Z", "close_time": "2022-02-07T20:25:00Z", "expected_expiration_time": "2022-02-01T15:00:00Z", "expiration_time": "2022-02-14T15:00:00Z", "latest_expiration_time": "2022-02-14T15:00:00Z", "settlement_timer_seconds": 10800, "status": "finalized", "response_price_units": "usd_cent", "notional_value": 100, "notional_value_dollars": [0, 0], "yes_bid": 99, "yes_bid_dollars": [0, 0], "yes_ask": 100, "yes_ask_dollars": [0, 0], "no_bid": 0, "no_bid_dollars": [0, 0], "no_ask": 1, "no_ask_dollars": [0, 0], "last_price": 98, "last_price_dollars": [0, 0], "previous_yes_bid": 99, "previous_yes_bid_dollars": [0, 0], "previous_yes_ask": 100, "previous_yes_ask_dollars": [0, 0], "previous_price": 98, "previous_price_dollars": [0, 0], "volume": 1539, "volume_24h": 0, "liquidity": 0, "liquidity_dollars": [0, 0], "open_interest": 760, "result": "yes", "settlement_value": 100, "can_close_early": true, "expiration_value": "1.92", "category": "", "risk_limit_cents": 0, "yes_topbook_liquidity_dollars": [0, 0], "no_topbook_liquidity_dollars": [0, 0], "rules_primary": "If the yield curve par rate for 10-year U.S. treasury notes is above 1.7% on February 07, 2022, then the market resolves to Yes.", "rules_secondary": "These par yields are derived from bid-side market price quotations at or near 3:30 PM each trading day.\n\nThe market will expire and close and expire at the sooner of the first 10:00 AM following the data release for February 07, 2022, or one week following February 07, 2022.", "tick_size": 1}, {"ticker": "TNOTE-22JAN31-T1.7", "event_ticker": "TNOTE-22JAN31", "market_type": "binary", "title": "Will the yield of 10-year U.S. treasury notes be above 1.7% on January 31, 2022?", "subtitle": ">1.7%", "yes_sub_title": "1.70%", "no_sub_title": "Outside 1.70%", "open_time": "2022-01-26T15:00:00Z", "close_time": "2022-01-31T20:25:00Z", "expected_expiration_time": "2022-01-26T15:00:00Z", "expiration_time": "2022-02-07T15:00:00Z", "latest_expiration_time": "2022-02-07T15:00:00Z", "settlement_timer_seconds": 10800, "status": "finalized", "response_price_units": "usd_cent", "notional_value": 100, "notional_value_dollars": [0, 0], "yes_bid": 99, "yes_bid_dollars": [0, 0], "yes_ask": 100, "yes_ask_dollars": [0, 0], "no_bid": 0, "no_bid_dollars": [0, 0], "no_ask": 1, "no_ask_dollars": [0, 0], "last_price": 99, "last_price_dollars": [0, 0], "previous_yes_bid": 99, "previous_yes_bid_dollars": [0, 0], "previous_yes_ask": 100, "previous_yes_ask_dollars": [0, 0], "previous_price": 99, "previous_price_dollars": [0, 0], "volume": 3457, "volume_24h": 51, "liquidity": 0, "liquidity_dollars": [0, 0], "open_interest": 2857, "result": "yes", "settlement_value": 100, "can_close_early": true, "expiration_value": "1.79", "category": "", "risk_limit_cents": 0, "yes_topbook_liquidity_dollars": [0, 0], "no_topbook_liquidity_dollars": [0, 0], "rules_primary": "If the yield curve par rate for 10-year U.S. treasury notes is above 1.7% on January 31, 2022, then the market resolves to Yes.", "rules_secondary": "These par yields are derived from bid-side market price quotations at or near 3:30 PM each trading day.\n\nThe market will expire and close and expire at the sooner of the first 10:00 AM following the data release for January 31, 2022, or one week following January 31, 2022.", "tick_size": 1}, {"ticker": "TNOTE-22JAN31-T1.8", "event_ticker": "TNOTE-22JAN31", "market_type": "binary", "title": "Will the yield of **10-year U.S. treasury notes** be above 1.8% on January 31, 2022?", "subtitle": ">1.8%", "yes_sub_title": "1.80%", "no_sub_title": "Outside 1.80%", "open_time": "2022-01-26T15:00:00Z", "close_time": "2022-01-31T20:25:00Z", "expected_expiration_time": "2022-01-26T15:00:00Z", "expiration_time": "2022-02-07T15:00:00Z", "latest_expiration_time": "2022-02-07T15:00:00Z", "settlement_timer_seconds": 10800, "status": "finalized", "response_price_units": "usd_cent", "notional_value": 100, "notional_value_dollars": [0, 0], "yes_bid": 0, "yes_bid_dollars": [0, 0], "yes_ask": 80, "yes_ask_dollars": [0, 0], "no_bid": 20, "no_bid_dollars": [0, 0], "no_ask": 100, "no_ask_dollars": [0, 0], "last_price": 69, "last_price_dollars": [0, 0], "previous_yes_bid": 0, "previous_yes_bid_dollars": [0, 0], "previous_yes_ask": 80, "previous_yes_ask_dollars": [0, 0], "previous_price": 69, "previous_price_dollars": [0, 0], "volume": 3576, "volume_24h": 147, "liquidity": 0, "liquidity_dollars": [0, 0], "open_interest": 1095, "result": "no", "settlement_value": 0, "can_close_early": true, "expiration_value": "1.79", "category": "", "risk_limit_cents": 0, "yes_topbook_liquidity_dollars": [0, 0], "no_topbook_liquidity_dollars": [0, 0], "rules_primary": "If the yield curve par rate for 10-year U.S. treasury notes is above 1.8% on January 31, 2022, then the market resolves to Yes.", "rules_secondary": "These par yields are derived from bid-side market price quotations at or near 3:30 PM each trading day.\n\nThe market will expire and close and expire at the sooner of the first 10:00 AM following the data release for January 31, 2022, or one week following January 31, 2022.", "tick_size": 1}, {"ticker": "TNOTE-22JAN31-T1.9", "event_ticker": "TNOTE-22JAN31", "market_type": "binary", "title": "Will the yield of **10-year U.S. treasury notes** be above 1.9% on January 31, 2022?", "subtitle": ">1.9%", "yes_sub_title": "1.90%", "no_sub_title": "Outside 1.90%", "open_time": "2022-01-26T15:00:00Z", "close_time": "2022-01-31T20:25:00Z", "expected_expiration_time": "2022-01-26T15:00:00Z", "expiration_time": "2022-02-07T15:00:00Z", "latest_expiration_time": "2022-02-07T15:00:00Z", "settlement_timer_seconds": 10800, "status": "finalized", "response_price_units": "usd_cent", "notional_value": 100, "notional_value_dollars": [0, 0], "yes_bid": 0, "yes_bid_dollars": [0, 0], "yes_ask": 1, "yes_ask_dollars": [0, 0], "no_bid": 99, "no_bid_dollars": [0, 0], "no_ask": 100, "no_ask_dollars": [0, 0], "last_price": 3, "last_price_dollars": [0, 0], "previous_yes_bid": 0, "previous_yes_bid_dollars": [0, 0], "previous_yes_ask": 1, "previous_yes_ask_dollars": [0, 0], "previous_price": 3, "previous_price_dollars": [0, 0], "volume": 2736, "volume_24h": 1, "liquidity": 0, "liquidity_dollars": [0, 0], "open_interest": 1958, "result": "no", "settlement_value": 0, "can_close_early": true, "expiration_value": "1.79", "category": "", "risk_limit_cents": 0, "yes_topbook_liquidity_dollars": [0, 0], "no_topbook_liquidity_dollars": [0, 0], "rules_primary": "If the yield curve par rate for 10-year U.S. treasury notes is above 1.9% on January 31, 2022, then the market resolves to Yes.", "rules_secondary": "These par yields are derived from bid-side market price quotations at or near 3:30 PM each trading day.\n\nThe market will expire and close and expire at the sooner of the first 10:00 AM following the data release for January 31, 2022, or one week following January 31, 2022.", "tick_size": 1}]}